gosling_widget/__init__.py
gosling_widget/_version.py
gosling_widget/widget.py
gosling_widget/labextension/package.json
gosling_widget/labextension/static/120.0be4ea0f1124579bf299.js
gosling_widget/labextension/static/120.0be4ea0f1124579bf299.js.LICENSE.txt
gosling_widget/labextension/static/313.061cf1ebb2e6567f47ef.js
gosling_widget/labextension/static/345.6e09c8f50fb36cfa77da.js
gosling_widget/labextension/static/589.73aa9b4adb77ad64168e.js
gosling_widget/labextension/static/589.73aa9b4adb77ad64168e.js.LICENSE.txt
gosling_widget/labextension/static/711.51bf4c662808672863ce.js
gosling_widget/labextension/static/771.d27d8e2d89a843290dc3.js
gosling_widget/labextension/static/771.d27d8e2d89a843290dc3.js.LICENSE.txt
gosling_widget/labextension/static/856.a11f777a91952ce36946.js
gosling_widget/labextension/static/856.a11f777a91952ce36946.js.LICENSE.txt
gosling_widget/labextension/static/879.2d24e8a8809b954c1df6.js
gosling_widget/labextension/static/940.9719ea36b42054500c41.js
gosling_widget/labextension/static/995.f96e1d8e4d52e90de17f.js
gosling_widget/labextension/static/remoteEntry.e1d0fe9d6cc7333b17d1.js
gosling_widget/labextension/static/style.js
gosling_widget/labextension/static/third-party-licenses.json
gosling_widget/nbextension/extension.js
gosling_widget/nbextension/index.js
gosling_widget-0.0.2.data/data/etc/jupyter/nbconfig/notebook.d/gosling-widget.json
gosling_widget-0.0.2.data/data/share/jupyter/labextensions/gosling-widget/package.json
gosling_widget-0.0.2.data/data/share/jupyter/labextensions/gosling-widget/static/120.0be4ea0f1124579bf299.js
gosling_widget-0.0.2.data/data/share/jupyter/labextensions/gosling-widget/static/120.0be4ea0f1124579bf299.js.LICENSE.txt
gosling_widget-0.0.2.data/data/share/jupyter/labextensions/gosling-widget/static/313.061cf1ebb2e6567f47ef.js
gosling_widget-0.0.2.data/data/share/jupyter/labextensions/gosling-widget/static/345.6e09c8f50fb36cfa77da.js
gosling_widget-0.0.2.dist-info/LICENSE
gosling_widget-0.0.2.dist-info/METADATA
gosling_widget-0.0.2.dist-info/WHEEL
gosling_widget-0.0.2.dist-info/top_level.txt
gosling_widget-0.0.2.dist-info/RECORD
