Metadata-Version: 2.1
Name: gosling-widget
Version: 0.0.2
Summary: A Jupyter Widget for Gosling
Home-page: https://github.com/gosling-lang/gosling-widget
Author: Trevor Manz
Author-email: trevor.j.manz@gmail.com
License: MIT
Platform: UNKNOWN
Requires-Python: >=3.7
License-File: LICENSE
Requires-Dist: ipywidgets
